{
	"credit": "Made with Blockbench",
	"textures": {
		"0": "block/dekorationen/geschirr-dekoration/salzstreuer",
		"particle": "block/dekorationen/geschirr-dekoration/salzstreuer"
	},
	"elements": [
		{
			"from": [6, 0, 6],
			"to": [10, 4, 10],
			"faces": {
				"north": {"uv": [0, 0, 4, 4], "texture": "#0"},
				"east": {"uv": [0, 4, 4, 8], "texture": "#0"},
				"south": {"uv": [4, 0, 8, 4], "texture": "#0"},
				"west": {"uv": [4, 4, 8, 8], "texture": "#0"},
				"up": {"uv": [4, 12, 0, 8], "texture": "#0"},
				"down": {"uv": [12, 0, 8, 4], "texture": "#0"}
			}
		},
		{
			"from": [7, 4, 7],
			"to": [9, 6, 9],
			"faces": {
				"north": {"uv": [4, 8, 6, 10], "texture": "#0"},
				"east": {"uv": [8, 4, 10, 6], "texture": "#0"},
				"south": {"uv": [6, 8, 8, 10], "texture": "#0"},
				"west": {"uv": [8, 6, 10, 8], "texture": "#0"},
				"up": {"uv": [10, 10, 8, 8], "texture": "#0"},
				"down": {"uv": [6, 10, 4, 12], "texture": "#0"}
			}
		}
	],
	"groups": [
		{
			"name": "group",
			"origin": [8, 8, 8],
			"color": 0,
			"children": [0, 1]
		}
	]
}